{
  "command-palette:open": [],
  "app:delete-file": [
    {
      "modifiers": [
        "Alt",
        "Shift"
      ],
      "key": "D"
    }
  ],
  "editor:delete-paragraph": [],
  "editor:focus-left": [],
  "editor:focus-right": [],
  "editor:swap-line-down": [
    {
      "modifiers": [
        "Alt"
      ],
      "key": "ArrowDown"
    }
  ],
  "editor:swap-line-up": [
    {
      "modifiers": [
        "Alt"
      ],
      "key": "ArrowUp"
    }
  ],
  "app:go-back": [
    {
      "modifiers": [
        "Ctrl"
      ],
      "key": "ArrowLeft"
    }
  ],
  "app:go-forward": [
    {
      "modifiers": [
        "Ctrl"
      ],
      "key": "ArrowRight"
    }
  ],
  "editor:open-search-replace": [
    {
      "modifiers": [
        "Mod"
      ],
      "key": "H"
    }
  ],
  "editor:toggle-blockquote": [
    {
      "modifiers": [
        "Ctrl"
      ],
      "key": "B"
    }
  ],
  "editor:toggle-code": [
    {
      "modifiers": [
        "Mod"
      ],
      "key": "E"
    }
  ],
  "editor:toggle-comments": [
    {
      "modifiers": [
        "Mod",
        "Shift"
      ],
      "key": "C"
    }
  ],
  "markdown:toggle-preview": [
    {
      "modifiers": [
        "Alt",
        "Ctrl"
      ],
      "key": " "
    }
  ],
  "editor:toggle-source": [
    {
      "modifiers": [
        "Ctrl"
      ],
      "key": " "
    }
  ],
  "editor:follow-link": [
    {
      "modifiers": [
        "Mod"
      ],
      "key": "Enter"
    }
  ],
  "editor:toggle-checklist-status": [],
  "file-explorer:new-file": [],
  "file-explorer:new-file-in-new-pane": [],
  "workspace:open-in-new-window": [
    {
      "modifiers": [
        "Mod",
        "Shift"
      ],
      "key": "N"
    }
  ],
  "templater-obsidian:jump-to-next-cursor-location": [
    {
      "modifiers": [
        "Shift"
      ],
      "key": "Tab"
    }
  ],
  "pane-relief:go-1st": [],
  "pane-relief:go-2nd": [],
  "pane-relief:go-3rd": [],
  "pane-relief:go-4th": [],
  "pane-relief:go-5th": [],
  "pane-relief:go-6th": [],
  "pane-relief:go-7th": [],
  "pane-relief:go-8th": [],
  "pane-relief:go-last": [],
  "pane-relief:go-prev": [],
  "pane-relief:go-next": [],
  "obsidian-outliner:unfold": [],
  "obsidian-outliner:move-list-item-up": [],
  "obsidian-outliner:move-list-item-down": [],
  "obsidian-outliner:fold": [],
  "switcher:open": [],
  "pane-relief:swap-next": [],
  "pane-relief:swap-prev": [],
  "pane-relief:put-1st": [],
  "pane-relief:put-2nd": [],
  "pane-relief:put-3rd": [],
  "pane-relief:put-4th": [],
  "pane-relief:put-5th": [],
  "pane-relief:put-6th": [],
  "pane-relief:put-7th": [],
  "pane-relief:put-8th": [],
  "pane-relief:put-last": [],
  "table-editor-obsidian:table-control-bar": [],
  "obsidian-editor-shortcuts:deleteLine": [
    {
      "modifiers": [
        "Mod"
      ],
      "key": "D"
    }
  ],
  "obsidian-editor-shortcuts:addCursorsToSelectionEnds": [],
  "obsidian-editor-shortcuts:duplicateLine": [],
  "obsidian-editor-shortcuts:deleteToStartOfLine": [
    {
      "modifiers": [
        "Mod"
      ],
      "key": "Backspace"
    }
  ],
  "obsidian-editor-shortcuts:goToLineEnd": [
    {
      "modifiers": [
        "Mod"
      ],
      "key": "ArrowRight"
    }
  ],
  "obsidian-editor-shortcuts:goToLineStart": [
    {
      "modifiers": [
        "Mod"
      ],
      "key": "ArrowLeft"
    }
  ],
  "obsidian-editor-shortcuts:insertLineAbove": [
    {
      "modifiers": [
        "Ctrl"
      ],
      "key": "A"
    }
  ],
  "obsidian-editor-shortcuts:insertLineBelow": [],
  "obsidian-editor-shortcuts:joinLines": [],
  "obsidian-editor-shortcuts:selectLine": [],
  "obsidian-editor-shortcuts:selectWordOrNextOccurrence": [
    {
      "modifiers": [
        "Ctrl",
        "Shift"
      ],
      "key": "ArrowRight"
    }
  ],
  "pane-relief:ordered-close": [],
  "app:toggle-left-sidebar": [
    {
      "modifiers": [
        "Ctrl"
      ],
      "key": "Home"
    }
  ],
  "app:toggle-right-sidebar": [
    {
      "modifiers": [
        "Ctrl"
      ],
      "key": "End"
    }
  ],
  "note-refactor-obsidian:app:extract-selection-content-only": [],
  "note-refactor-obsidian:app:extract-selection-first-line": [
    {
      "modifiers": [
        "Ctrl"
      ],
      "key": "-"
    }
  ],
  "darlal-switcher-plus:switcher-plus:open": [
    {
      "modifiers": [
        "Mod"
      ],
      "key": "P"
    }
  ],
  "advanced-cursors:add-cursor-above": [],
  "advanced-cursors:add-cursor-below": [],
  "advanced-cursors:add-prev-match-to-selections": [
    {
      "modifiers": [
        "Ctrl",
        "Shift"
      ],
      "key": "ArrowLeft"
    }
  ],
  "obsidian-better-command-palette:open-better-commmand-palette": [
    {
      "modifiers": [
        "Shift"
      ],
      "key": " "
    }
  ],
  "obsidian-advanced-new-file:advanced-new-file-new-pane": [],
  "templater-obsidian:create-new-note-from-template": [
    {
      "modifiers": [
        "Alt"
      ],
      "key": "N"
    }
  ],
  "templater-obsidian:insert-templater": [
    {
      "modifiers": [
        "Alt",
        "Ctrl",
        "Mod",
        "Shift"
      ],
      "key": " "
    }
  ],
  "obsidian-table-to-csv-exporter:obsidian-table-to-csv-exporter": [
    {
      "modifiers": [
        "Alt",
        "Shift"
      ],
      "key": "X"
    }
  ],
  "obsidian-git:commit-specified-message": [
    {
      "modifiers": [
        "Alt"
      ],
      "key": "C"
    },
    {
      "modifiers": [
        "Alt"
      ],
      "key": "G"
    }
  ],
  "obsidian-git:push2": [
    {
      "modifiers": [
        "Alt"
      ],
      "key": "P"
    }
  ],
  "file-explorer:move-file": [
    {
      "modifiers": [
        "Ctrl"
      ],
      "key": "M"
    }
  ],
  "periodic-notes:open-daily-note": [
    {
      "modifiers": [
        "Ctrl"
      ],
      "key": "D"
    }
  ],
  "periodic-notes:open-weekly-note": [
    {
      "modifiers": [
        "Alt"
      ],
      "key": "W"
    }
  ],
  "periodic-notes:open-yearly-note": [
    {
      "modifiers": [
        "Alt"
      ],
      "key": "Y"
    }
  ],
  "periodic-notes:open-quarterly-note": [
    {
      "modifiers": [
        "Alt"
      ],
      "key": "Q"
    }
  ],
  "periodic-notes:open-monthly-note": [
    {
      "modifiers": [
        "Alt"
      ],
      "key": "M"
    }
  ],
  "workspace:toggle-pin": [
    {
      "modifiers": [
        "Ctrl"
      ],
      "key": "P"
    }
  ],
  "obsidian-zotero-desktop-connector:zdc-exp-Zotero Import": [
    {
      "modifiers": [
        "Alt"
      ],
      "key": "Z"
    }
  ],
  "obsidian-zotero-desktop-connector:show-zotero-debug-view": [
    {
      "modifiers": [
        "Ctrl"
      ],
      "key": "Z"
    }
  ],
  "url-into-selection:paste-url-into-selection": [
    {
      "modifiers": [
        "Alt"
      ],
      "key": "V"
    }
  ],
  "workspace:next-tab": [
    {
      "modifiers": [
        "Alt",
        "Mod"
      ],
      "key": "ArrowRight"
    }
  ],
  "workspace:previous-tab": [
    {
      "modifiers": [
        "Alt",
        "Mod"
      ],
      "key": "ArrowLeft"
    }
  ],
  "app:reload": [
    {
      "modifiers": [
        "Mod"
      ],
      "key": "R"
    }
  ],
  "copy-note:copy-note": [
    {
      "modifiers": [
        "Alt"
      ],
      "key": "D"
    }
  ],
  "obsidian-editor-shortcuts:goToNextHeading": [
    {
      "modifiers": [
        "Alt",
        "Ctrl"
      ],
      "key": "ArrowDown"
    }
  ],
  "obsidian-editor-shortcuts:goToPrevHeading": [
    {
      "modifiers": [
        "Alt",
        "Ctrl"
      ],
      "key": "ArrowUp"
    }
  ],
  "obsidian-editor-shortcuts:insertCursorAbove": [
    {
      "modifiers": [
        "Alt",
        "Mod"
      ],
      "key": "ArrowUp"
    }
  ],
  "obsidian-editor-shortcuts:insertCursorBelow": [
    {
      "modifiers": [
        "Alt",
        "Mod"
      ],
      "key": "ArrowDown"
    }
  ],
  "heycalmdown-navigate-cursor-history:cursor-position-backward": [],
  "heycalmdown-navigate-cursor-history:cursor-position-forward": [],
  "workspace:close-others": [
    {
      "modifiers": [
        "Ctrl"
      ],
      "key": "C"
    }
  ],
  "obsidian-editor-shortcuts:indent-using-tabs": [
    {
      "modifiers": [
        "Shift"
      ],
      "key": "Tab"
    }
  ]
}